jass_bot/__init__.py
jass_bot/experiment.py
jass_bot/hyper_parameters.py
jass_bot/jass_policy.py
jass_bot/util.py
jass_bot/zeromq_server.py
jass_bot/cfr/__init__.py
jass_bot/mcts/__init__.py
jass_bot/mcts/ismcts.py
jass_bot/mcts/knockout_whist.py
jass_bot/mcts/president.py
jass_bot/rl/__init__.py
jass_bot/rl/experiment.py
jass_bot/rl/hyper_parameters.py
jass_bot/rl/jass_policy.py
jass_bot/rl/util.py
jass_bot-0.0.6.dist-info/METADATA
jass_bot-0.0.6.dist-info/RECORD
jass_bot-0.0.6.dist-info/WHEEL
jass_bot-0.0.6.dist-info/top_level.txt
