Metadata-Version: 2.1
Name: jass-bot
Version: 0.0.6
Summary: An AI for the Schieber variant of the Swiss card game Jassen
Home-page: https://github.com/JoelNiklaus/JassBot
Author: Joel Niklaus
Author-email: me@joelniklaus.ch
License: MIT License
Requires-Dist: gym (>=0.10.8)
Requires-Dist: gym-jass (>=0.1.16)
Requires-Dist: schieber (>=0.1.8)
